vtb_jinja2_addons/__about__.py
vtb_jinja2_addons/__init__.py
vtb_jinja2_addons/extensions.py
vtb_jinja2_addons/filters.py
vtb_jinja2_addons-0.0.1.dist-info/METADATA
vtb_jinja2_addons-0.0.1.dist-info/WHEEL
vtb_jinja2_addons-0.0.1.dist-info/top_level.txt
vtb_jinja2_addons-0.0.1.dist-info/RECORD
